nlb_catalogue_client/__init__.py
nlb_catalogue_client/api/__init__.py
nlb_catalogue_client/api/catalogue/__init__.py
nlb_catalogue_client/api/catalogue/get_get_availability_info.py
nlb_catalogue_client/api/catalogue/get_get_most_checkouts_trends_titles.py
nlb_catalogue_client/api/catalogue/get_get_new_titles.py
nlb_catalogue_client/api/catalogue/get_get_title_details.py
nlb_catalogue_client/api/catalogue/get_get_titles.py
nlb_catalogue_client/api/catalogue/get_search_titles.py
nlb_catalogue_client/client.py
nlb_catalogue_client/errors.py
nlb_catalogue_client/models/__init__.py
nlb_catalogue_client/models/bad_request_error.py
nlb_catalogue_client/models/bib_format.py
nlb_catalogue_client/models/book_cover.py
nlb_catalogue_client/models/checkouts_title.py
nlb_catalogue_client/models/checkouts_trend.py
nlb_catalogue_client/models/course_code.py
nlb_catalogue_client/models/facet.py
nlb_catalogue_client/models/facet_data.py
nlb_catalogue_client/models/get_availability_info_response_v2.py
nlb_catalogue_client/models/get_title_details_response_v2.py
nlb_catalogue_client/models/get_titles_response_v2.py
nlb_catalogue_client/models/internal_server_error.py
nlb_catalogue_client/models/item.py
nlb_catalogue_client/models/location.py
nlb_catalogue_client/models/media.py
nlb_catalogue_client/models/method_not_allowed_error.py
nlb_catalogue_client/models/new_arrival_title.py
nlb_catalogue_client/models/not_found_error.py
nlb_catalogue_client/models/not_implemented_error.py
nlb_catalogue_client/models/search_most_checkouts_titles_response.py
nlb_catalogue_client/models/search_new_titles_response_v2.py
nlb_catalogue_client/models/search_titles_response_v2.py
nlb_catalogue_client/models/service_unavailable_error.py
nlb_catalogue_client/models/status.py
nlb_catalogue_client/models/title.py
nlb_catalogue_client/models/title_record.py
nlb_catalogue_client/models/title_summary.py
nlb_catalogue_client/models/too_many_requests_error.py
nlb_catalogue_client/models/transaction_status.py
nlb_catalogue_client-2.dist-info/METADATA
nlb_catalogue_client-2.dist-info/WHEEL
nlb_catalogue_client-2.dist-info/RECORD
